Workbook

Sheet 2. Universe
B2: STEP I — SELECT THE UNIVERSE OF COMPARABLE COMPANIES
B5: Candidate | C5: Listed? | D5: Country | E5: End market | F5: Include? | G5: final call | H5: Rationale / notes
B6: Tesco (TARGET) | C6: Yes | D6: UK | E6: Food retail | F6: TARGET | G6: include | H6: The company you are valuing.
B7: J Sainsbury | C7: Yes | D7: UK | E7: Food retail | F7: Yes | G7: Core COMP | H7: Closest listed UK peer — same market, similar model, comparable size.
B8: Marks & Spencer | C8: Yes | D8: UK | E8: Food + clothing | F8: Scrutinise | G8: Scruitinise due to selling not just food but clothing/home business | H8: Large food business, but clothing/home muddies the comparison. Include with care.
B9: Ocado Group | C9: Yes | D9: UK | E9: Grocery tech / logistics | F9: Exclude | G9: Exclude as value skewed due to it being not just grocery company but a tech one | H9: TRAP. Trades as a tech/logistics platform, not a grocer — thin or negative EBITDA, valued on totally different metrics.
B10: Carrefour | C10: Yes | D10: France | E10: Food retail | F10: Yes | G10: Core COMP | H10: Large European grocer — good peer, reports in EUR (multiples still comparable).
B11: Ahold Delhaize | C11: Yes | D11: Netherlands | E11: Food retail | F11: Yes | G11: Core COMP | H11: Big European/US grocer, EUR reporter — solid comparable.
B12: Jeronimo Martins | C12: Yes | D12: Portugal | E12: Food retail | F12: Yes | G12: Core COMP | H12: Pure-play European food retailer, EUR.
B13: Colruyt | C13: Yes | D13: Belgium | E13: Food retail | F13: Yes | G13: Core COMP | H13: Belgian grocer, EUR — reasonable peer.
B14: Kroger | C14: Yes | D14: USA | E14: Food retail | F14: Peripheral | G14: completrly Different continent to taregt | H14: US grocer. Different geography — use as secondary reference, not core.
B15: Wm Morrison | C15: No | D15: UK | E15: Food retail | F15: Exclude | G15: Not listed | H15: TRAP. Taken PRIVATE by CD&R in 2021 — no longer listed, so no market data to use.
B16: Asda | C16: No | D16: UK | E16: Food retail | F16: Exclude | G16: Not listed | H16: Private (Issa brothers / TDR). Not listed — no share price.
... B18: B&M European Value Retail | C18: Yes | D18: UK | E18: General merchandise | F18: Scruitinise | G18: not in mian group due to the end market being different and a lot smaller | H18: Private. Direct competitors, but no public data.

Sheet 3. Comp Sheet
A1: STEPS II & III — INPUT PAGE: locate financials & spread key statistics, ratios and multiples
B3: SHARE & CAPITAL INPUTS | J3: SHARE BRIDGE → EQUITY VALUE | P3: EV BRIDGE | V3: FINANCIALS (LTM) | AA3: MARGINS | AF3: TRADING MULTIPLES | AJ3: CREDIT & GROWTH
A4: Company | B4: Currency | C4: FX to GBP | D4: Share price | E4: 52-wk high | F4: % of 52wk | G4: Basic shares | H4: Options | I4: Exercise price (WAEP) | J4: Net option sh. | K4: Convert principal | L4: Conversion px | M4: Convert shares | N4: FD shares | O4: Equity value | P4: Total debt | Q4: Cash | R4: Preferred | S4: Minority int. | T4: Enterprise value | U4: EV (GBP m) | V4: Sales | W4: Gross profit | X4: EBITDA | Y4: EBIT | Z4: Net income | AA4: Diluted EPS | AB4: Gross mgn | AC4: EBITDA mgn | AD4: EBIT mgn | AE4: Net mgn | AF4: EV/Sales | AG4: EV/EBITDA | AH4: EV/EBIT | AI4: P/E | AJ4: Net debt/EBITDA | AK4: Prior-yr sales | AL4: Sales growth
C5: GBP per 1 | D5: local | E5: local | G5: m | H5: m | I5: local | J5: m | K5: m | L5: local | M5: m | N5: m | O5: local m | P5: m | Q5: m | R5: m | S5: m | T5: local m | U5: GBP m | V5: m | W5: m | X5: m | Y5: m | Z5: m | AA5: local | AK5: m
A6: Tesco (TARGET) | B6: £ | C6: 1 | D6: 4.7 | E6: 5.1 | F6: =IFERROR(D6/E6,"") -> 0.92156863 | G6: 6736841762 | H6: 199109811 | I6: 2.25 | J6: =IF(AND(D6>0,I6>0,D6>I6),H6-(H6*I6/D6),0) -> 1.0379128e+08 | K6: 0 | L6: 0 | M6: =IF(AND(L6>0,D6>L6),K6/L6,0) -> 0 | N6: =G6+J6+M6 -> 6.840633e+09 | O6: =D6*N6 -> 3.2150975e+10 | P6: 14666000000 | Q6: 2255000000 | R6: 0 | S6: 4000000 | T6: =O6+(P6-IF(M6>0,K6,0))+R6+S6-Q6 -> 4.4565975e+10 | U6: =T6*C6 -> 4.4565975e+10 | V6: 69916000000 | W6: 5051000000 | X6: 4825000000 | Y6: 3128000000 | Z6: 1626000000 | AA6: =IFERROR(Z6/N6,"") -> 0.2376973 | AB6: =IFERROR(W6/V6,"") -> 0.072243835 | AC6: =IFERROR(X6/V6,"") -> 0.069011385 | AD6: =IFERROR(Y6/V6,"") -> 0.044739402 | AE6: =IFERROR(Z6/V6,"") -> 0.023256479 | AF6: =IFERROR(T6/V6,"") -> 0.6374217 | AG6: =IFERROR(T6/X6,"") -> 9.2364716 | AH6: =IFERROR(T6/Y6,"") -> 14.247435 | AI6: =IFERROR(O6/Z6,"") -> 19.773048 | AJ6: =IFERROR((P6-IF(M6>0,K6,0)-Q6)/X6,"") -> 2.572228 | AK6: 68187000000 | AL6: =IFERROR(V6/AK6-1,"") -> 0.02535674
A7: J Sainsbury | B7: £ | C7: 1 | D7: 3.32 | E7: 3.71 | F7: =IFERROR(D7/E7,"") -> 0.89487871 | G7: 2339424088 | H7: 55400000 | I7: 1.95 | J7: =IF(AND(D7>0,I7>0,D7>I7),H7-(H7*I7/D7),0) -> 22860843 | K7: 0 | L7: 0 | M7: =IF(AND(L7>0,D7>L7),K7/L7,0) -> 0 | N7: =G7+J7+M7 -> 2.3622849e+09 | O7: =D7*N7 -> 7.842786e+09 | P7: 6616000000 | Q7: 2777000000 | R7: 0 | S7: 0 | T7: =O7+(P7-IF(M7>0,K7,0))+R6+S7-Q7 -> 1.1681786e+10 | U7: =T7*C7 -> 1.1681786e+10 | V7: 32812000000 | W7: 2221000000 | X7: 2192000000 | Y7: 1036000000 | Z7: 242000000 | AA7: =IFERROR(Z7/N7,"") -> 0.10244319 | AB7: =IFERROR(W7/V7,"") -> 0.06768865 | AC7: =IFERROR(X7/V7,"") -> 0.066804828 | AD7: =IFERROR(Y7/V7,"") -> 0.031573814 | AE7: =IFERROR(Z7/V7,"") -> 0.0073753505 | AF7: =IFERROR(T7/V7,"") -> 0.35602176 | AG7: =IFERROR(T7/X7,"") -> 5.3292819 | AH7: =IFERROR(T7/Y7,"") -> 11.275855 | AI7: =IFERROR(O7/Z7,"") -> 32.408206 | AJ7: =IFERROR((P7-IF(M7>0,K7,0)-Q7)/X7,"") -> 1.7513686 | AK7: 32238000000 | AL7: =IFERROR(V7/AK7-1,"") -> 0.017805075
A8: Carrefour | B8: € | C8: 0.86 | D8: 15.88 | E8: 17.54 | F8: =IFERROR(D8/E8,"") -> 0.90535918 | G8: 706233789 | H8: 0 | I8: 0 | J8: =IF(AND(D8>0,I8>0,D8>I8),H8-(H8*I8/D8),0) -> 0 | K8: 0 | L8: 0 | M8: =IF(AND(L8>0,D8>L8),K8/L8,0) -> 0 | N8: =G8+J8+M8 -> 706233789 | O8: =D8*N8 -> 1.1214993e+10 | P8: 15529000000 | Q8: 6179000000 | R8: 0 | S8: 693000000 | T8: =O8+(P8-IF(M8>0,K8,0))+R8+S8-Q8 -> 2.1257993e+10 | U8: =T8*C8 -> 1.8281874e+10 | V8: 84025000000 | W8: 16024000000 | X8: 4506000000 | Y8: 2158000000 | Z8: 319000000 | AA8: =IFERROR(Z8/N8,"") -> 0.45169178 | AB8: =IFERROR(W8/V8,"") -> 0.19070515 | AC8: =IFERROR(X8/V8,"") -> 0.053626897 | AD8: =IFERROR(Y8/V8,"") -> 0.025682832 | AE8: =IFERROR(Z8/V8,"") -> 0.0037964891 | AF8: =IFERROR(T8/V8,"") -> 0.25299604 | AG8: =IFERROR(T8/X8,"") -> 4.7177081 | AH8: =IFERROR(T8/Y8,"") -> 9.8507843 | AI8: =IFERROR(O8/Z8,"") -> 35.156717 | AJ8: =IFERROR((P8-IF(M8>0,K8,0)-Q8)/X8,"") -> 2.0750111 | AK8: 83454000000 | AL8: =IFERROR(V8/AK8-1,"") -> 0.0068420926
A9: Ahold Delhaize | B9: € | C9: 0.86 | D9: 35.42 | E9: 42.54 | F9: =IFERROR(D9/E9,"") -> 0.83262811 | G9: 886689000 | H9: 0 | I9: 0 | J9: =IF(AND(D9>0,I9>0,D9>I9),H9-(H9*I9/D9),0) -> 0 | K9: 0 | L9: 0 | M9: =IF(AND(L9>0,D9>L9),K9/L9,0) -> 0 | N9: =G9+J9+M9 -> 886689000 | O9: =D9*N9 -> 31406524380 | P9: 18404000000 | Q9: 3705000000 | R9: 0 | S9: 0 | T9: =O9+(P9-IF(M9>0,K9,0))+R9+S9-Q9 -> 46105524380 | U9: =T9*C9 -> 3.9650751e+10 | V9: 92352000000 | W9: 24514000000 | X9: 7319000000 | Y9: 3734000000 | Z9: 2264000000 | AA9: =IFERROR(Z9/N9,"") -> 2.5533191 | AB9: =IFERROR(W9/V9,"") -> 0.26544092 | AC9: =IFERROR(X9/V9,"") -> 0.079251126 | AD9: =IFERROR(Y9/V9,"") -> 0.040432259 | AE9: =IFERROR(Z9/V9,"") -> 0.0245149 | AF9: =IFERROR(T9/V9,"") -> 0.49923688 | AG9: =IFERROR(T9/X9,"") -> 6.2994295 | AH9: =IFERROR(T9/Y9,"") -> 12.347489 | AI9: =IFERROR(O9/Z9,"") -> 13.87214 | AJ9: =IFERROR((P9-IF(M9>0,K9,0)-Q9)/X9,"") -> 2.0083345 | AK9: 89356000000 | AL9: =IFERROR(V9/AK9-1,"") -> 0.033528806
A10: Jeronimo Martins | B10: € | C10: 0.86 | D10: 16.31 | E10: 23.24 | F10: =IFERROR(D10/E10,"") -> 0.70180723 | G10: 628434220 | H10: 0 | I10: 0 | J10: =IF(AND(D10>0,I10>0,D10>I10),H10-(H10*I10/D10),0) -> 0 | K10: 0 | L10: 0 | M10: =IF(AND(L10>0,D10>L10),K10/L10,0) -> 0 | N10: =G10+J10+M10 -> 628434220 | O10: =D10*N10 -> 1.0249762e+10 | P10: 5560000000 | Q10: 2268000000 | R10: 0 | S10: 238000000 | T10: =O10+(P10-IF(M10>0,K10,0))+R10+S10-Q10 -> 1.3779762e+10 | U10: =T10*C10 -> 1.1850595e+10 | V10: 35991000000 | W10: 7434000000 | X10: 2480000000 | Y10: 1338000000 | Z10: 646000000 | AA10: =IFERROR(Z10/N10,"") -> 1.0279517 | AB10: =IFERROR(W10/V10,"") -> 0.20655164 | AC10: =IFERROR(X10/V10,"") -> 0.068906115 | AD10: =IFERROR(Y10/V10,"") -> 0.037175961 | AE10: =IFERROR(Z10/V10,"") -> 0.017948932 | AF10: =IFERROR(T10/V10,"") -> 0.38286689 | AG10: =IFERROR(T10/X10,"") -> 5.5563557 | AH10: =IFERROR(T10/Y10,"") -> 10.298776 | AI10: =IFERROR(O10/Z10,"") -> 15.866505 | AJ10: =IFERROR((P10-IF(M10>0,K10,0)-Q10)/X10,"") -> 1.3274194 | AK10: 33464000000 | AL10: =IFERROR(V10/AK10-1,"") -> 0.075513985
A11: Colruyt | B11: € | C11: 0.86 | D11: 36.24 | E11: 38.44 | F11: =IFERROR(D11/E11,"") -> 0.94276795 | G11: 120910372 | H11: 0 | I11: 0 | J11: =IF(AND(D11>0,I11>0,D11>I11),H11-(H11*I11/D11),0) -> 0 | K11: 0 | L11: 0 | M11: =IF(AND(L11>0,D11>L11),K11/L11,0) -> 0 | N11: =G11+J11+M11 -> 120910372 | O11: =D11*N11 -> 4.3817919e+09 | P11: 995000000 | Q11: 627000000 | R11: 0 | S11: 400000 | T11: =O11+(P11-IF(M11>0,K11,0))+R11+S11-Q11 -> 4.7501919e+09 | U11: =T11*C11 -> 4.085165e+09 | V11: 10963000000 | W11: 3288000000 | X11: 859000000 | Y11: 446000000 | Z11: 337000000 | AA11: =IFERROR(Z11/N11,"") -> 2.7871885 | AB11: =IFERROR(W11/V11,"") -> 0.29991791 | AC11: =IFERROR(X11/V11,"") -> 0.078354465 | AD11: =IFERROR(Y11/V11,"") -> 0.040682295 | AE11: =IFERROR(Z11/V11,"") -> 0.030739761 | AF11: =IFERROR(T11/V11,"") -> 0.43329307 | AG11: =IFERROR(T11/X11,"") -> 5.5299091 | AH11: =IFERROR(T11/Y11,"") -> 10.650654 | AI11: =IFERROR(O11/Z11,"") -> 13.00235 | AJ11: =IFERROR((P11-IF(M11>0,K11,0)-Q11)/X11,"") -> 0.42840512 | AK11: 10845000000 | AL11: =IFERROR(V11/AK11-1,"") -> 0.01088059
A12: Kroger | B12: $ | C12: 0.75 | D12: 57.48 | E12: 76.58 | F12: =IFERROR(D12/E12,"") -> 0.75058762 | G12: 612633958 | H12: 6102811 | I12: 48.97 | J12: =IF(AND(D12>0,I12>0,D12>I12),H12-(H12*I12/D12),0) -> 903530.3 | K12: 0 | L12: 0 | M12: =IF(AND(L12>0,D12>L12),K12/L12,0) -> 0 | N12: =G12+J12+M12 -> 6.1353749e+08 | O12: =D12*N12 -> 3.5266135e+10 | P12: 25105000000 | Q12: 3959000000 | R12: 0 | S12: 4000000 | T12: =O12+(P12-IF(M12>0,K12,0))+R12+S12-Q12 -> 5.6416135e+10 | U12: =T12*C12 -> 4.2312101e+10 | V12: 147123000000 | W12: 32748000000 | X12: 7095000000 | Y12: 3849000000 | Z12: 2665000000 | AA12: =IFERROR(Z12/N12,"") -> 4.3436629 | AB12: =IFERROR(W12/V12,"") -> 0.22258926 | AC12: =IFERROR(X12/V12,"") -> 0.048224955 | AD12: =IFERROR(Y12/V12,"") -> 0.026161783 | AE12: =IFERROR(Z12/V12,"") -> 0.018114095 | AF12: =IFERROR(T12/V12,"") -> 0.38346237 | AG12: =IFERROR(T12/X12,"") -> 7.9515342 | AH12: =IFERROR(T12/Y12,"") -> 14.657349 | AI12: =IFERROR(O12/Z12,"") -> 13.233071 | AJ12: =IFERROR((P12-IF(M12>0,K12,0)-Q12)/X12,"") -> 2.9804087 | AK12: 150039000000 | AL12: =IFERROR(V12/AK12-1,"") -> -0.019434947
F14: =IFERROR(D14/E14,"") | AA14: =IFERROR(Z14/N14,"") | AB14: =IFERROR(W14/V14,"") | AC14: =IFERROR(X14/V14,"") | AD14: =IFERROR(Y14/V14,"") | AE14: =IFERROR(Z14/V14,"") | AF14: =IFERROR(T14/V14,"") | AG14: =IFERROR(T14/X14,"") | AH14: =IFERROR(T14/Y14,"") | AI14: =IFERROR(O14/Z14,"") | AJ14: =IFERROR((P14-IF(M14>0,K14,0)-Q14)/X14,"") | AL14: =IFERROR(V14/AK14-1,"")

Sheet 4. Benchmark
B2: STEP IV — BENCHMARK THE COMPARABLE COMPANIES
B5: Company | C5: EBITDA mgn | D5: EV/Sales | E5: EV/EBITDA | F5: EV/EBIT | G5: P/E | H5: Net debt/EBITDA
B6: Tesco (TARGET) | C6: ='3. Comp Sheet'!AC6 -> 0.069011385 | D6: ='3. Comp Sheet'!AF6 -> 0.6374217 | E6: ='3. Comp Sheet'!AG6 -> 9.2364716 | F6: ='3. Comp Sheet'!AH6 -> 14.247435 | G6: ='3. Comp Sheet'!AI6 -> 19.773048 | H6: ='3. Comp Sheet'!AJ6 -> 2.572228
B7: =IF('3. Comp Sheet'!A7="","",'3. Comp Sheet'!A7) -> J Sainsbury | C7: ='3. Comp Sheet'!AC7 -> 0.066804828 | D7: ='3. Comp Sheet'!AF7 -> 0.35602176 | E7: ='3. Comp Sheet'!AG7 -> 5.3292819 | F7: ='3. Comp Sheet'!AH7 -> 11.275855 | G7: ='3. Comp Sheet'!AI7 -> 32.408206 | H7: ='3. Comp Sheet'!AJ7 -> 1.7513686
B8: =IF('3. Comp Sheet'!A8="","",'3. Comp Sheet'!A8) -> Carrefour | C8: ='3. Comp Sheet'!AC8 -> 0.053626897 | D8: ='3. Comp Sheet'!AF8 -> 0.25299604 | E8: ='3. Comp Sheet'!AG8 -> 4.7177081 | F8: ='3. Comp Sheet'!AH8 -> 9.8507843 | G8: ='3. Comp Sheet'!AI8 -> 35.156717 | H8: ='3. Comp Sheet'!AJ8 -> 2.0750111
B9: =IF('3. Comp Sheet'!A9="","",'3. Comp Sheet'!A9) -> Ahold Delhaize | C9: ='3. Comp Sheet'!AC9 -> 0.079251126 | D9: ='3. Comp Sheet'!AF9 -> 0.49923688 | E9: ='3. Comp Sheet'!AG9 -> 6.2994295 | F9: ='3. Comp Sheet'!AH9 -> 12.347489 | G9: ='3. Comp Sheet'!AI9 -> 13.87214 | H9: ='3. Comp Sheet'!AJ9 -> 2.0083345
B10: =IF('3. Comp Sheet'!A10="","",'3. Comp Sheet'!A10) -> Jeronimo Martins | C10: ='3. Comp Sheet'!AC10 -> 0.068906115 | D10: ='3. Comp Sheet'!AF10 -> 0.38286689 | E10: ='3. Comp Sheet'!AG10 -> 5.5563557 | F10: ='3. Comp Sheet'!AH10 -> 10.298776 | G10: ='3. Comp Sheet'!AI10 -> 15.866505 | H10: ='3. Comp Sheet'!AJ10 -> 1.3274194
B11: =IF('3. Comp Sheet'!A11="","",'3. Comp Sheet'!A11) -> Colruyt | C11: ='3. Comp Sheet'!AC11 -> 0.078354465 | D11: ='3. Comp Sheet'!AF11 -> 0.43329307 | E11: ='3. Comp Sheet'!AG11 -> 5.5299091 | F11: ='3. Comp Sheet'!AH11 -> 10.650654 | G11: ='3. Comp Sheet'!AI11 -> 13.00235 | H11: ='3. Comp Sheet'!AJ11 -> 0.42840512
B12: =IF('3. Comp Sheet'!A12="","",'3. Comp Sheet'!A12) -> Kroger | C12: ='3. Comp Sheet'!AC12 -> 0.048224955 | D12: ='3. Comp Sheet'!AF12 -> 0.38346237 | E12: ='3. Comp Sheet'!AG12 -> 7.9515342 | F12: ='3. Comp Sheet'!AH12 -> 14.657349 | G12: ='3. Comp Sheet'!AI12 -> 13.233071 | H12: ='3. Comp Sheet'!AJ12 -> 2.9804087
B13: =IF('3. Comp Sheet'!A13="","",'3. Comp Sheet'!A13)
B14: =IF('3. Comp Sheet'!A14="","",'3. Comp Sheet'!A14) | C14: ='3. Comp Sheet'!AC14 | D14: ='3. Comp Sheet'!AF14 | E14: ='3. Comp Sheet'!AG14 | F14: ='3. Comp Sheet'!AH14 | G14: ='3. Comp Sheet'!AI14 | H14: ='3. Comp Sheet'!AJ14
B16: Mean | C16: =IFERROR(AVERAGE(C7:C14),"") -> 0.065861398 | D16: =IFERROR(AVERAGE(D7:D14),"") -> 0.38464617 | E16: =IFERROR(AVERAGE(E7:E14),"") -> 5.8973697 | F16: =IFERROR(AVERAGE(F7:F14),"") -> 11.513485 | G16: =IFERROR(AVERAGE(G7:G14),"") -> 20.589831 | H16: =IFERROR(AVERAGE(H7:H14),"") -> 1.7618246
B17: Median | C17: =IFERROR(MEDIAN(C7:C14),"") -> 0.067855471 | D17: =IFERROR(MEDIAN(D7:D14),"") -> 0.38316463 | E17: =IFERROR(MEDIAN(E7:E14),"") -> 5.5431324 | F17: =IFERROR(MEDIAN(F7:F14),"") -> 10.963255 | G17: =IFERROR(MEDIAN(G7:G14),"") -> 14.869322 | H17: =IFERROR(MEDIAN(H7:H14),"") -> 1.8798515
B18: High | C18: =IFERROR(MAX(C7:C14),"") -> 0.079251126 | D18: =IFERROR(MAX(D7:D14),"") -> 0.49923688 | E18: =IFERROR(MAX(E7:E14),"") -> 7.9515342 | F18: =IFERROR(MAX(F7:F14),"") -> 14.657349 | G18: =IFERROR(MAX(G7:G14),"") -> 35.156717 | H18: =IFERROR(MAX(H7:H14),"") -> 2.9804087
B19: Low | C19: =IFERROR(MIN(C7:C14),"") -> 0.048224955 | D19: =IFERROR(MIN(D7:D14),"") -> 0.25299604 | E19: =IFERROR(MIN(E7:E14),"") -> 4.7177081 | F19: =IFERROR(MIN(F7:F14),"") -> 9.8507843 | G19: =IFERROR(MIN(G7:G14),"") -> 13.00235 | H19: =IFERROR(MIN(H7:H14),"") -> 0.42840512
B21: "EV/EBITDA - Tesco trades at 9.2x vs the peer median of 5.5x (peer range 4.7x-8.0x) - Tesco sits at the expensive end: its enterprise value is high relative to the EBITDA it generates compared with peers - the market pays a higher price per unit of earnings for Tesco - However, the premium is much smaller on P/E (19.8x vs 14.9x median, ~33%) than on EV/EBITDA (~67%). Because EV/EBITDA capitalises Tesco's £7.7bn of lease liabilities into EV while P/E ignores debt, a large part of the apparent EV/EBITDA premium reflects Tesco's lease-heavy store estate rather than an equity-level valuation premium - Growth does not explain the premium: Tesco grew sales +2.5% while Jeronimo Martins (+7.6%) and Ahold Delhaize (+3.4%) grew faster yet trade on lower multiples - P/E is distorted across the set by one-off items below the operating line (Carrefour's Italy disposal, Sainsbury's Financial Services exit), so primary weight is placed on EV/EBITDA and EV/EBIT read together"

Sheet 5. Valuation
B2: STEP V — DETERMINE VALUATION
C5: Low | D5: Mid | E5: High
B6: EV/EBITDA multiple | C6: 4.7 | D6: =IFERROR(AVERAGE(C6,E6),"") -> 6.35 | E6: 8
B7: Tesco EBITDA (local m) | C7: ='3. Comp Sheet'!X6 -> 4825000000 | D7: ='3. Comp Sheet'!X6 -> 4825000000 | E7: ='3. Comp Sheet'!X6 -> 4825000000
B8: Implied Enterprise Value (m) | C8: =IFERROR(C6*C7,"") -> 22677500000 | D8: =IFERROR(D6*D7,"") -> 30638750000 | E8: =IFERROR(E6*E7,"") -> 38600000000
B9: less: Net debt (Debt - in-the-money Convert - Cash) | C9: =-('3. Comp Sheet'!P6-IF('3. Comp Sheet'!M6>0,'3. Comp Sheet'!K6,0)-'3. Comp Sheet'!Q6) -> -12411000000 | D9: =-('3. Comp Sheet'!P6-IF('3. Comp Sheet'!M6>0,'3. Comp Sheet'!K6,0)-'3. Comp Sheet'!Q6) -> -12411000000 | E9: =-('3. Comp Sheet'!P6-IF('3. Comp Sheet'!M6>0,'3. Comp Sheet'!K6,0)-'3. Comp Sheet'!Q6) -> -12411000000
B10: less: Preferred | C10: =-'3. Comp Sheet'!R6 -> 0 | D10: =-'3. Comp Sheet'!R6 -> 0 | E10: =-'3. Comp Sheet'!R6 -> 0
B11: less: Minority interest | C11: =-'3. Comp Sheet'!S6 -> -4000000 | D11: =-'3. Comp Sheet'!S6 -> -4000000 | E11: =-'3. Comp Sheet'!S6 -> -4000000
B12: Implied Equity Value (m) | C12: =IFERROR(C8+C9+C10+C11,"") -> 10262500000 | D12: =IFERROR(D8+D9+D10+D11,"") -> 18223750000 | E12: =IFERROR(E8+E9+E10+E11,"") -> 26185000000
B13: FD shares (m) | C13: ='3. Comp Sheet'!N6 -> 6.840633e+09 | D13: ='3. Comp Sheet'!N6 -> 6.840633e+09 | E13: ='3. Comp Sheet'!N6 -> 6.840633e+09
B14: Implied share price (local) | C14: =IFERROR(C12/C13,"") -> 1.5002267 | D14: =IFERROR(D12/D13,"") -> 2.6640444 | E14: =IFERROR(E12/E13,"") -> 3.8278621
B15: Implied share price (pence, if UK) | C15: =IFERROR(C14*100,"") -> 150.02267 | D15: =IFERROR(D14*100,"") -> 266.40444 | E15: =IFERROR(E14*100,"") -> 382.78621
B17: Current share price (from tab 3) | C17: ='3. Comp Sheet'!D6 -> 4.7
B18: Implied upside/(downside) at Mid | C18: =IFERROR(D14/C17-1,"") -> -0.43318205
B20: On a pure peer-multiple basis, Tesco appears to trade at a substantial premium (£4.70 actual vs. £1.50–£3.83 implied). This likely reflects factors comps analysis doesn't fully capture such as Tesco's UK market leadership. Also comps method does have its limits as it tells you relative value not the intrinsic value so its entitely possible for an entire sector to be overvalued by the market.
